djpp/__init__.py
djpp/pyproject.py
django_pyproject-1.0.6.dist-info/LICENSE
django_pyproject-1.0.6.dist-info/WHEEL
django_pyproject-1.0.6.dist-info/METADATA
django_pyproject-1.0.6.dist-info/RECORD
