Metadata-Version: 2.1
Name: django-pyproject
Version: 1.0.6
Summary: A package for storing Django settings in pyproject.toml.
Home-page: https://github.com/Ceterai/django-pyproject
License: MIT
Author: Ceterai
Author-email: ceterai@protonmail.com
Requires-Python: >=3.8,<4.0
Classifier: License :: OSI Approved :: MIT License
Classifier: Operating System :: OS Independent
Classifier: Programming Language :: Python :: 3
Classifier: Programming Language :: Python :: 3.8
Requires-Dist: toml (>=0.10.0,<0.11.0)
Project-URL: Repository, https://github.com/Ceterai/django-pyproject
